{
  "type": "Feature",
  "properties": {
    "iso:country":"UK",
    "name:bul_x_preferred":[
        "\u0416\u0435\u0440\u0435\u0431\u043a\u043e\u0432\u0435"
    ],
    "name:chi_x_preferred":[
        "\u71b1\u5217\u5e03\u79d1\u97cb"
    ],
    "name:eng_x_preferred":[
        "Zherebkove"
    ],
    "name:ger_x_preferred":[
        "Scherebkowe"
    ],
    "name:lav_x_preferred":[
        "\u017derebkove"
    ],
    "name:rum_x_preferred":[
        "Jerebkove"
    ],
    "name:rus_x_preferred":[
        "\u0416\u0435\u0440\u0435\u0431\u043a\u043e\u0432\u043e"
    ],
    "name:spa_x_preferred":[
        "Zherebkove"
    ],
    "name:ukr_x_preferred":[
        "Zherebkove"
    ],
    "name:ukr_x_variant":[
        "\u0416\u0435\u0440\u0435\u0431\u043a\u043e\u0432\u0435"
    ],
    "name:unk_x_variant":[
        "Sherebkovo"
    ],
    "qs:a0":"\u0423\u043a\u0440\u0430\u0457\u043d\u0430",
    "qs:a1":"*\u041e\u0434\u0435\u0441\u044c\u043a\u0430",
    "qs:a1_alt":"Odes'ka",
    "qs:a1r":"0",
    "qs:a2":"\u0410\u043d\u0430\u043d\u044c\u0457\u0432\u0441\u044c\u043a\u0438\u0439",
    "qs:a2_alt":"Anan'ivs'kyi",
    "qs:adm0":"\u0423\u043a\u0440\u0430\u0457\u043d\u0430",
    "qs:la_lc":"*",
    "qs:level":"locality",
    "qs:loc":"\u0416\u0435\u0440\u0435\u0431\u043a\u043e\u0432\u0435",
    "qs:loc_alt":"Zherebkove",
    "qs:pop":0,
    "qs:type":"buffered point",
    "wof:name":"\u0416\u0435\u0440\u0435\u0431\u043a\u043e\u0432\u0435",
    "wof:placetype":"locality"
},
  "geometry": {"coordinates":[29.877514,47.833728],"type":"Point"}
}