{
  "type": "Feature",
  "properties": {
    "iso:country":"UK",
    "name:chi_x_preferred":[
        "\u65b0\u591a\u83f2\u5c3c\u592b\u5361"
    ],
    "name:eng_x_preferred":[
        "Nova Dofinivka"
    ],
    "name:ger_x_preferred":[
        "Nowa Dofiniwka"
    ],
    "name:lav_x_preferred":[
        "Nova Dofi\u0146ivka"
    ],
    "name:rum_x_preferred":[
        "Nova Dofinivka"
    ],
    "name:rus_x_preferred":[
        "\u041d\u043e\u0432\u0430\u044f \u0414\u043e\u0444\u0438\u043d\u043e\u0432\u043a\u0430"
    ],
    "name:ukr_x_preferred":[
        "\u041d\u043e\u0432\u0430 \u0414\u043e\u0444\u0456\u043d\u0456\u0432\u043a\u0430"
    ],
    "name:unk_x_variant":[
        "Dofinovka"
    ],
    "qs:a0":"\u0423\u043a\u0440\u0430\u0457\u043d\u0430",
    "qs:a1":"*\u041e\u0434\u0435\u0441\u044c\u043a\u0430",
    "qs:a1_alt":"Odes'ka",
    "qs:a1r":"0",
    "qs:a2":"\u041a\u043e\u043c\u0456\u043d\u0442\u0435\u0440\u043d\u0456\u0432\u0441\u044c\u043a\u0438\u0439",
    "qs:a2_alt":"Kominternivs'kyi",
    "qs:adm0":"\u0423\u043a\u0440\u0430\u0457\u043d\u0430",
    "qs:la_lc":"*",
    "qs:level":"locality",
    "qs:loc":"\u041d\u043e\u0432\u0430 \u0414\u043e\u0444\u0456\u043d\u0456\u0432\u043a\u0430",
    "qs:loc_alt":"Nova Dofinivka",
    "qs:pop":0,
    "qs:type":"buffered point",
    "wof:name":"\u041d\u043e\u0432\u0430 \u0414\u043e\u0444\u0456\u043d\u0456\u0432\u043a\u0430",
    "wof:placetype":"locality"
},
  "geometry": {"coordinates":[30.910689,46.576722],"type":"Point"}
}